rebyte_langchain/__init__.py
rebyte_langchain/rebyte_langchain.py
rebyte_langchain/version.py
rebyte_langchain-0.0.12.dist-info/LICENSE
rebyte_langchain-0.0.12.dist-info/METADATA
rebyte_langchain-0.0.12.dist-info/WHEEL
rebyte_langchain-0.0.12.dist-info/top_level.txt
rebyte_langchain-0.0.12.dist-info/zip-safe
rebyte_langchain-0.0.12.dist-info/RECORD
