Metadata-Version: 2.1
Name: rebyte_langchain
Version: 0.0.12
Summary: Python langchain-like client library for the Rebyte API
Home-page: https://github.com/ReByteAI/rebyte-langchain-SDK
Author: Rebyte team
Author-email: support@rebyte.ai
Classifier: Programming Language :: Python :: 3
Classifier: License :: OSI Approved :: MIT License
Classifier: Operating System :: OS Independent
Requires-Python: >=3.7.1
License-File: LICENSE
Requires-Dist: requests >=2.20
Requires-Dist: typing-extensions
Requires-Dist: aiohttp
Requires-Dist: rebyte >=0.0.4
Requires-Dist: langchain >=0.0.240
Provides-Extra: dev
Requires-Dist: black ~=21.6b0 ; extra == 'dev'
Requires-Dist: pytest ==6.* ; extra == 'dev'
Requires-Dist: pytest-asyncio ; extra == 'dev'
Requires-Dist: pytest-mock ; extra == 'dev'
